kaf_pas/__init__.py
kaf_pas/accounting/__init__.py
kaf_pas/accounting/management/__init__.py
kaf_pas/accounting/migrations/0001_initial.py
kaf_pas/accounting/migrations/0002_buffers.py
kaf_pas/accounting/migrations/0003_auto_20200119_1607.py
kaf_pas/accounting/migrations/0004_tmp_buffer_edizm.py
kaf_pas/accounting/migrations/0005_auto_20200119_1744.py
kaf_pas/accounting/migrations/0006_tmp_buffer_description.py
kaf_pas/accounting/migrations/0007_tmp_buffer_value_off.py
kaf_pas/accounting/migrations/0008_tmp_buffer_color.py
kaf_pas/accounting/migrations/0009_remove_tmp_buffer_color.py
kaf_pas/accounting/migrations/0010_tmp_buffer_color.py
kaf_pas/accounting/migrations/0011_tmp_buffer_props.py
kaf_pas/accounting/migrations/0012_auto_20200704_1858.py
kaf_pas/accounting/migrations/0013_auto_20200705_0346.py
kaf_pas/accounting/migrations/0014_auto_20200705_0357.py
kaf_pas/accounting/migrations/0015_auto_20200705_0400.py
kaf_pas/accounting/migrations/0016_tmp_buffer_resource.py
kaf_pas/accounting/migrations/0017_auto_20200705_0638.py
kaf_pas/accounting/migrations/0018_tmp_buffer_launch.py
kaf_pas/accounting/migrations/0019_auto_20200709_0739.py
kaf_pas/accounting/migrations/0020_auto_20200709_0741.py
kaf_pas/accounting/migrations/0021_remove_tmp_buffer_resource.py
kaf_pas/accounting/migrations/__init__.py
kaf_pas/accounting/models/__init__.py
kaf_pas/accounting/models/buffer_ext.py
kaf_pas/accounting/models/buffers.py
kaf_pas/accounting/models/posting_items.py
kaf_pas/accounting/models/tmp_buffer.py
kaf_pas/accounting/models/write_off_items.py
kaf_pas/accounting/urls/__init__.py
kaf_pas/accounting/urls/buffers.py
kaf_pas/accounting/urls/posting_items.py
kaf_pas/accounting/urls/tmp_buffer.py
kaf_pas/accounting/urls/tmp_buffer_off.py
kaf_pas/accounting/urls/write_off_items.py
kaf_pas/accounting/views/__init__.py
kaf_pas/accounting/views/buffers.py
kaf_pas/accounting/views/posting_items.py
kaf_pas/accounting/views/tmp_buffer.py
kaf_pas/accounting/views/tmp_buffer_off.py
kaf_pas-0.0.121.dist-info/LICENSE.txt
kaf_pas-0.0.121.dist-info/METADATA
kaf_pas-0.0.121.dist-info/WHEEL
kaf_pas-0.0.121.dist-info/entry_points.txt
kaf_pas-0.0.121.dist-info/top_level.txt
kaf_pas-0.0.121.dist-info/RECORD
