Metadata-Version: 2.1
Name: kaf-pas
Version: 0.0.121
Summary: ISC Python common project
Home-page: UNKNOWN
Author: Andrey Yudin
Author-email: uag@ivc-inform.ru
License: UNKNOWN
Project-URL: Source, http://toucan.simplesys.lan/scm-manager/git/ivc-inform/kaf-pas
Keywords: isc setuptools development common kaf-pas
Platform: UNKNOWN
Classifier: Development Status :: 3 - Alpha
Classifier: Intended Audience :: Developers
Classifier: Topic :: Software Development :: Build Tools
Classifier: License :: OSI Approved :: MIT License
Classifier: Programming Language :: Python :: 3.7
Classifier: Programming Language :: Python :: 3.6
Requires-Python: >=3.6
